README.md
setup.py
adevinta_yapo_bi_connect_db/__init__.py
adevinta_yapo_bi_connect_db.egg-info/PKG-INFO
adevinta_yapo_bi_connect_db.egg-info/SOURCES.txt
adevinta_yapo_bi_connect_db.egg-info/dependency_links.txt
adevinta_yapo_bi_connect_db.egg-info/not-zip-safe
adevinta_yapo_bi_connect_db.egg-info/top_level.txt