Metadata-Version: 1.0
Name: adevinta-yapo-bi-connect-db
Version: 0.0.0.0.15
Summary: Class develop to connect db.
Home-page: https://github.mpi-internal.com/Yapo/bi-insights
Author: Yapo BI
Author-email: bi.insights@yapo.cl
License: MIT
Platform: UNKNOWN
